{"title":"Setting up OBS for webcasting","markdown":{"yaml":{"title":"Setting up OBS for webcasting","image":"img/quarto.jpg","date":"last-modified","execute":{"message":false,"warning":false}},"headingText":"Introduction","containsRefs":false,"markdown":"\n\n\n\n\nWebcasting for biostatistics is the challenge. \n\nLets take it one step at a time. \n\nStart with the open source project `OBS`. \n\n[ Welcome | OBS ]( https://obsproject.com/welcome)\n\n"},"formats":{"html":{"execute":{"fig-width":7,"fig-height":5,"fig-format":"retina","fig-dpi":96,"df-print":"default","error":false,"eval":true,"cache":null,"freeze":false,"echo":true,"output":true,"warning":false,"include":true,"keep-md":false,"keep-ipynb":false,"ipynb":null,"enabled":null,"daemon":null,"daemon-restart":false,"debug":false,"ipynb-filters":[],"message":false,"engine":"markdown"},"render":{"keep-tex":false,"keep-source":false,"keep-hidden":false,"prefer-html":false,"output-divs":true,"output-ext":"html","fig-align":"default","fig-pos":null,"fig-env":null,"code-fold":"none","code-overflow":"scroll","code-link":false,"code-line-numbers":false,"code-tools":false,"tbl-colwidths":"auto","merge-includes":true,"latex-auto-mk":true,"latex-auto-install":true,"latex-clean":true,"latex-max-runs":10,"latex-makeindex":"makeindex","latex-makeindex-opts":[],"latex-tlmgr-opts":[],"latex-input-paths":[],"latex-output-dir":null,"link-external-icon":false,"link-external-newwindow":false,"self-contained-math":false,"format-resources":[]},"pandoc":{"standalone":true,"wrap":"none","default-image-extension":"png","to":"html","number-sections":true,"css":["../../styles.css"],"toc":true,"html-math-method":"katex","include-in-header":{"file":"../../header.html"},"output-file":"index.html"},"language":{},"metadata":{"lang":"en","fig-responsive":true,"quarto-version":"1.2.313","theme":"tango","license":"CC BY","toc-title":"Table of contents","toc-location":"left","author":[{"name":"Ronald (Ryy) Glenn Thomas","url":"https://rgtlab.org","affiliation":"UCSD","affiliation-url":"https://ucsd.edu","orcid":"0000-0003-1686-4965"}],"citation":true,"comments":{"giscus":{"repo":"rgt47/qblog","repo-id":"R_kgDOH6TO7A","category":"Announcements","category-id":"DIC_kwDOH5G3U84CRUp9","mapping":"pathname","reactions-enabled":true,"loading":"lazy","input-position":"bottom","theme":"light"}},"title":"Setting up OBS for webcasting","image":"img/quarto.jpg","date":"last-modified"},"extensions":{"book":{"multiFile":true}}},"pdf":{"execute":{"fig-width":5.5,"fig-height":3.5,"fig-format":"pdf","fig-dpi":300,"df-print":"default","error":false,"eval":true,"cache":null,"freeze":false,"echo":true,"output":true,"warning":false,"include":true,"keep-md":false,"keep-ipynb":false,"ipynb":null,"enabled":null,"daemon":null,"daemon-restart":false,"debug":false,"ipynb-filters":[],"message":false,"engine":"markdown"},"render":{"keep-tex":false,"keep-source":false,"keep-hidden":false,"prefer-html":false,"output-divs":true,"output-ext":"pdf","fig-align":"default","fig-pos":null,"fig-env":null,"code-fold":"none","code-overflow":"scroll","code-link":false,"code-line-numbers":false,"code-tools":false,"tbl-colwidths":true,"merge-includes":true,"latex-auto-mk":true,"latex-auto-install":true,"latex-clean":true,"latex-max-runs":10,"latex-makeindex":"makeindex","latex-makeindex-opts":[],"latex-tlmgr-opts":[],"latex-input-paths":[],"latex-output-dir":null,"link-external-icon":false,"link-external-newwindow":false,"self-contained-math":false,"format-resources":[]},"pandoc":{"pdf-engine":"xelatex","standalone":true,"variables":{"graphics":true,"tables":true},"default-image-extension":"pdf","to":"pdf","number-sections":true,"toc":true,"output-file":"index.pdf"},"language":{},"metadata":{"block-headings":true,"margin-left":"30mm","margin-right":"60mm","license":"CC BY","toc-title":"Table of contents","toc-location":"left","author":[{"name":"Ronald (Ryy) Glenn Thomas","url":"https://rgtlab.org","affiliation":"UCSD","affiliation-url":"https://ucsd.edu","orcid":"0000-0003-1686-4965"}],"citation":true,"comments":{"giscus":{"repo":"rgt47/qblog","repo-id":"R_kgDOH6TO7A","category":"Announcements","category-id":"DIC_kwDOH5G3U84CRUp9","mapping":"pathname","reactions-enabled":true,"loading":"lazy","input-position":"bottom","theme":"light"}},"title":"Setting up OBS for webcasting","image":"img/quarto.jpg","date":"last-modified"},"extensions":{"book":{}}}}}